entropy/__init__.py
entropy/core/component.py
entropy/core/mixture.py
entropy/core/multiphase_component.py
entropy/core/phase.py
entropy/functions/filtering.py
entropy/functions/phase.py
entropy/models/__init__.py
entropy/models/eos/__init__.py
entropy/models/eos/base.py
entropy/models/eos/constant_volume.py
entropy/models/eos/ideal_gas.py
entropy/models/eos/peng_robinson.py
entropy/models/eos/simplified_iapws.py
entropy/models/heat_capacity/__init__.py
entropy/models/heat_capacity/base.py
entropy/models/heat_capacity/constant_heat_capacity.py
entropy/models/heat_capacity/nasa.py
entropy/models/heat_capacity/shomate.py
entropy/models/heat_capacity/thermo_interval.py
entropy/models/serializable_mixin.py
entropy/utils/atomic_weight.py
entropy/utils/constants.py
entropy/utils/math.py
entropy/utils/unit_registry.py
entropy_sim-1.0.11.dist-info/LICENSE
entropy_sim-1.0.11.dist-info/METADATA
entropy_sim-1.0.11.dist-info/WHEEL
entropy_sim-1.0.11.dist-info/RECORD
