Metadata-Version: 2.1
Name: entropy-sim
Version: 1.0.11
Summary: A lightweight Python library for modeling chemical mixtures.
License: CC BY-NC
Author: Milo Knowles
Author-email: miloknowles97@gmail.com
Requires-Python: >=3.10,<4.0
Classifier: License :: Other/Proprietary License
Classifier: Programming Language :: Python :: 3
Classifier: Programming Language :: Python :: 3.10
Classifier: Programming Language :: Python :: 3.11
Classifier: Programming Language :: Python :: 3.12
Requires-Dist: numpy (>=1.21.3,<2.0.0)
Requires-Dist: pint (>=0.20.0,<1.0.0)
Requires-Dist: pydantic (>=2.1.0,<3.0.0)
